lipid_librarian/LipidQuery.py
lipid_librarian/__init__.py
lipid_librarian/cli.py
lipid_librarian/api/Alex123API.py
lipid_librarian/api/LinexAPI.py
lipid_librarian/api/LipidAPI.py
lipid_librarian/api/LipidMapsAPI.py
lipid_librarian/api/LipidOntologyAPI.py
lipid_librarian/api/SwissLipidsAPI.py
lipid_librarian/api/__init__.py
lipid_librarian/data/adducts.csv
lipid_librarian/data/alex123/alex123_db.h5
lipid_librarian/data/linex/linex_data.pbz2
lipid_librarian/data/lipid_ontology/lion_association.tsv
lipid_librarian/data/lipid_ontology/lion_graph.tsv
lipid_librarian/lipid/Adduct.py
lipid_librarian/lipid/DatabaseIdentifier.py
lipid_librarian/lipid/Fragment.py
lipid_librarian/lipid/Level.py
lipid_librarian/lipid/Lipid.py
lipid_librarian/lipid/Mass.py
lipid_librarian/lipid/Nomenclature.py
lipid_librarian/lipid/OntologyTerm.py
lipid_librarian/lipid/Reaction.py
lipid_librarian/lipid/Source.py
lipid_librarian/lipid/StructureIdentifier.py
lipid_librarian/lipid/Synonym.py
lipid_librarian/lipid/__init__.py
lipid_librarian-0.1.2b0.dist-info/LICENSE
lipid_librarian-0.1.2b0.dist-info/METADATA
lipid_librarian-0.1.2b0.dist-info/WHEEL
lipid_librarian-0.1.2b0.dist-info/entry_points.txt
lipid_librarian-0.1.2b0.dist-info/top_level.txt
lipid_librarian-0.1.2b0.dist-info/RECORD
