Metadata-Version: 2.1
Name: lipid-librarian
Version: 0.1.2b0
Summary: A Lipidomics Database Explorer Package
Author: Felix Niedermeier, Konstantinos Mechteridis, Konstantin Pelz
Project-URL: Bug Reports, https://github.com/lipitum/lipid_librarian/issues
Project-URL: Source, https://github.com/lipitum/lipid_librarian/
Keywords: lipids,bioinformatics,development
Classifier: Programming Language :: Python :: 3
Classifier: License :: OSI Approved :: GNU Affero General Public License v3 or later (AGPLv3+)
Classifier: Intended Audience :: Science/Research
Classifier: Natural Language :: English
Classifier: Operating System :: OS Independent
Classifier: Operating System :: POSIX :: Linux
Classifier: Topic :: Database :: Front-Ends
Classifier: Topic :: Scientific/Engineering :: Bio-Informatics
Classifier: Programming Language :: Python :: 3
Requires-Python: >=3.10
License-File: LICENSE
Requires-Dist: requests
Requires-Dist: importlib-metadata
Requires-Dist: numpy
Requires-Dist: pandas
Requires-Dist: tables
Requires-Dist: jsons
Requires-Dist: json2html
Requires-Dist: SQLAlchemy
Requires-Dist: PyMySQL
Requires-Dist: networkx
Requires-Dist: ratelimit
Requires-Dist: func-timeout
Requires-Dist: liputils
Requires-Dist: sparql-dataframe
Requires-Dist: pygoslin
Requires-Dist: linex2
Provides-Extra: dev
Requires-Dist: pytest ; extra == 'dev'
Requires-Dist: flake8 ; extra == 'dev'
Requires-Dist: rpy2 ; extra == 'dev'
Provides-Extra: lint
Requires-Dist: flake8 ; extra == 'lint'
Provides-Extra: test
Requires-Dist: pytest ; extra == 'test'
